odoo/addons/web_send_message_popup/README.rst
odoo/addons/web_send_message_popup/__init__.py
odoo/addons/web_send_message_popup/__manifest__.py
odoo/addons/web_send_message_popup/i18n/fa.po
odoo/addons/web_send_message_popup/i18n/it.po
odoo/addons/web_send_message_popup/i18n/web_send_message_popup.pot
odoo/addons/web_send_message_popup/readme/CONTRIBUTORS.md
odoo/addons/web_send_message_popup/readme/DESCRIPTION.md
odoo/addons/web_send_message_popup/static/description/icon.png
odoo/addons/web_send_message_popup/static/description/index.html
odoo/addons/web_send_message_popup/static/src/chatter/web/chatter_patch.esm.js
odoo_addon_web_send_message_popup-18.0.1.0.0.2.dist-info/METADATA
odoo_addon_web_send_message_popup-18.0.1.0.0.2.dist-info/WHEEL
odoo_addon_web_send_message_popup-18.0.1.0.0.2.dist-info/top_level.txt
odoo_addon_web_send_message_popup-18.0.1.0.0.2.dist-info/RECORD
